<?xml version = "1.0" encoding = "UTF-8"?>
<beans xmlns="http://www.springframework.org/schema/beans"   xmlns:xsi="http://www.w3.org/2001/XMLSchema-instance"   xmlns:util="http://www.springframework.org/schema/util"   xsi:schemaLocation="     http://www.springframework.org/schema/beans http://www.springframework.org/schema/beans/spring-beans-3.0.xsd     http://www.springframework.org/schema/util  http://www.springframework.org/schema/util/spring-util-3.0.xsd">
 <bean id="COPY_ADDR_TO_CUST" class="com.chbank.t24.bean.DataPatchConfig">  <property name="transform" value="fix_address_id.xsl" /><!--   <property name="target" value="F_DE_ADDRESS" />  <property name="targetType">   <util:constant static-field="com.chbank.t24.bean.DataPatchConfig.TABLE" />  </property>  <property name="targetMode">   <util:constant static-field="com.chbank.t24.bean.DataPatchConfig.UPDATE" />    </property> -->
  <property name="target" value="./F_DE_ADDRESS.DAT"/>  <property name="targetType">   <util:constant static-field="com.chbank.t24.bean.DataPatchConfig.FILE" />  </property>    <property name="source">   <value><![CDATA[SELECT   D.RECID "recid",   D.XMLRECORD as "address" FROM F_DE_ADDRESS DWHERE D.RECID = 'HK0019999.PRINT.1'/* WHERE EXTRACTVALUE(D.XMLRECORD, '/row/@id') <> D.RECID */  ]]>   </value>  </property>  <property name="sourceType">   <util:constant static-field="com.chbank.t24.bean.DataPatchConfig.SQL" />    </property>   </bean></beans>        
